distillation/__init__.py
distillation/solvers.py
distillation/amundson_1958/__init__.py
distillation/amundson_1958/main.py
distillation/bubble_point/__init__.py
distillation/bubble_point/calculation.py
distillation/equilibrium_data/__init__.py
distillation/equilibrium_data/critical_properties.py
distillation/equilibrium_data/depriester.csv
distillation/equilibrium_data/depriester_charts.py
distillation/equilibrium_data/heat_capacity_liquid.csv
distillation/equilibrium_data/heat_capacity_liquid.py
distillation/equilibrium_data/heat_capacity_vapor.py
distillation/equilibrium_data/heats_of_vaporization.csv
distillation/equilibrium_data/heats_of_vaporization.py
distillation/unit_conversions/__init__.py
distillation/unit_conversions/pressure.py
distillation/unit_conversions/temperature.py
tests/__init__.py
tests/component_mass_balances.py
tests/equilibrium_data.py
distillation-0.1.1.dist-info/LICENSE
distillation-0.1.1.dist-info/METADATA
distillation-0.1.1.dist-info/WHEEL
distillation-0.1.1.dist-info/top_level.txt
distillation-0.1.1.dist-info/RECORD
